pyrems/__init__.py
pyrems/cli/__init__.py
pyrems/cli/decorators.py
pyrems/cli/main.py
pyrems/core.py
pyrems/handlers.py
pyrems/managers/__init__.py
pyrems/managers/records_manager.py
pyrems/managers/system_manager.py
pyrems/utils.py
pyrems/validation.py
pyrems-0.1.1.dist-info/WHEEL
pyrems-0.1.1.dist-info/entry_points.txt
pyrems-0.1.1.dist-info/METADATA
pyrems-0.1.1.dist-info/RECORD
