Metadata-Version: 2.3
Name: pyrems
Version: 0.1.1
Summary: Add your description here
Requires-Dist: click>=8.3.0
Requires-Dist: rich>=13.0.0
Requires-Python: >=3.12
